README.md
setup.cfg
setup.py
dovecot_cram_md5/__init__.py
dovecot_cram_md5.egg-info/PKG-INFO
dovecot_cram_md5.egg-info/SOURCES.txt
dovecot_cram_md5.egg-info/dependency_links.txt
dovecot_cram_md5.egg-info/top_level.txt