Metadata-Version: 1.0
Name: dovecot-cram-md5
Version: 0.1
Summary: Provide HMAC-MD5 hash for Dovecot
Home-page: UNKNOWN
Author: Asad Saeed
Author-email: UNKNOWN
License: GPL
Keywords: dovecot cram hmac md5
Platform: UNKNOWN
